[{"id": "btccom_23", "btc_price": 7535.69, "buy_url": "https://console.pool.bitcoin.com/confirmorderguest?contractid=23&hashrate=10&language=en", "coin": "BTC", "contract_cost": 0.182311575723863, "contract_size": 10.0, "daily_rate": 0.00010745978202786333, "duration": 180, "electricity_fee": 0.1, "expected_breakeven_days": 391.58920208057447, "expected_discount": -0.318424156815164, "honeyLemon_contract_name": "BTC 180 Days", "issuers": "btccom", "management_fee": 0.0, "messari": 0.04, "mining_payoff": 0.1382799115, "mining_payoff_btc": 1.835e-05, "present_value_of_total_cost": 328.1608363029534, "present_value_of_total_electricity_fee": 178.26083630295335, "sold_percent": 10.0, "today_income": 0.1382799115, "update_time": 1578330401, "upfront_fee": 149.9}, {"id": "btccom_42", "btc_price": 7535.69, "buy_url": "https://console.pool.bitcoin.com/confirmorderguest?contractid=42&hashrate=1&language=en", "coin": "BTC", "contract_cost": 0.2054794520547945, "contract_size": 1.0, "daily_rate": 0.00010745978202786333, "duration": 365, "electricity_fee": 0.0, "expected_breakeven_days": 542.3781313311009, "expected_discount": -0.48596748309890647, "honeyLemon_contract_name": "BTC 365 Days", "issuers": "btccom", "management_fee": 0.0, "messari": 0.04, "mining_payoff": 0.1382799115, "mining_payoff_btc": 1.835e-05, "present_value_of_total_cost": 75.0, "present_value_of_total_electricity_fee": 0.0, "sold_percent": 10.0, "today_income": 0.1382799115, "update_time": 1578330401, "upfront_fee": 75.0}, {"id": "btccom_38", "btc_price": 7535.69, "buy_url": "https://console.pool.bitcoin.com/confirmorderguest?contractid=38&hashrate=5&language=en", "coin": "BTC", "contract_cost": 0.16652483747291794, "contract_size": 5.0, "daily_rate": 0.00010745978202786333, "duration": 365, "electricity_fee": 0.1, "expected_breakeven_days": 652.8228258834927, "expected_discount": -0.20425906891702006, "honeyLemon_contract_name": "BTC 365 Days", "issuers": "btccom", "management_fee": 0.0, "messari": 0.04, "mining_payoff": 0.1382799115, "mining_payoff_btc": 1.835e-05, "present_value_of_total_cost": 303.90782838807525, "present_value_of_total_electricity_fee": 178.95782838807523, "sold_percent": 10.0, "today_income": 0.1382799115, "update_time": 1578330401, "upfront_fee": 124.94999999999999}, {"id": "btccom_23_bch", "btc_price": 235.4, "buy_url": "https://console.pool.bitcoin.com/confirmorderguest?contractid=23&hashrate=10&language=en", "coin": "bch", "contract_cost": 0.182311575723863, "contract_size": 10.0, "daily_rate": 0.00010745978202786333, "duration": 180, "electricity_fee": 0.1, "expected_breakeven_days": 286.65936281303294, "expected_discount": -0.19711829781153356, "honeyLemon_contract_name": "BCH 180 Days", "issuers": "btccom", "management_fee": 0.0, "messari": 0.04, "mining_payoff": 0.15229203, "mining_payoff_btc": 0.00064695, "present_value_of_total_cost": 328.1608363029534, "present_value_of_total_electricity_fee": 178.26083630295335, "sold_percent": 10.0, "today_income": 0.15229203, "update_time": 1578330401, "upfront_fee": 149.9}, {"id": "btccom_42_bch", "btc_price": 235.4, "buy_url": "https://console.pool.bitcoin.com/confirmorderguest?contractid=42&hashrate=1&language=en", "coin": "bch", "contract_cost": 0.2054794520547945, "contract_size": 1.0, "daily_rate": 0.00010745978202786333, "duration": 365, "electricity_fee": 0.0, "expected_breakeven_days": 492.4748852582765, "expected_discount": -0.3492462609815794, "honeyLemon_contract_name": "BCH 365 Days", "issuers": "btccom", "management_fee": 0.0, "messari": 0.04, "mining_payoff": 0.15229203, "mining_payoff_btc": 0.00064695, "present_value_of_total_cost": 75.0, "present_value_of_total_electricity_fee": 0.0, "sold_percent": 10.0, "today_income": 0.15229203, "update_time": 1578330401, "upfront_fee": 75.0}, {"id": "btccom_38_bch", "btc_price": 235.4, "buy_url": "https://console.pool.bitcoin.com/confirmorderguest?contractid=38&hashrate=5&language=en", "coin": "bch", "contract_cost": 0.16652483747291794, "contract_size": 5.0, "daily_rate": 0.00010745978202786333, "duration": 365, "electricity_fee": 0.1, "expected_breakeven_days": 477.8930938424078, "expected_discount": -0.09345733636171194, "honeyLemon_contract_name": "BCH 365 Days", "issuers": "btccom", "management_fee": 0.0, "messari": 0.04, "mining_payoff": 0.15229203, "mining_payoff_btc": 0.00064695, "present_value_of_total_cost": 303.90782838807525, "present_value_of_total_electricity_fee": 178.95782838807523, "sold_percent": 10.0, "today_income": 0.15229203, "update_time": 1578330401, "upfront_fee": 124.94999999999999}]